{
	"dataFile": "suratITMSDPtest.json",
	"genType": "spatio-temporal",
	"spatio-temporal": {
		"duplicateDetection": [
			"trip_id",
			"observationDateTime"
		],
		"suppressCols": [
			"trip_direction",
			"last_stop_id",
			"last_stop_arrival_time",
			"route_id",
			"actual_trip_start_time",
			"trip_delay",
			"vehicle_label",
			"id",
			"location.type",
			"trip_id"
		],
		"locationCol": "location.coordinates",
		"datetimeCol": "observationDateTime",
		"groupByCol": "license_plate",
    		"localityFactor": 1,
    		"globalMaxSpeed": 150,
    		"globalMinSpeed": 0,
    		"privacyLossBudgetEpsQuery1": 10,
		"privacyLossBudgetEpsQuery2": 10,
		"h3Resolution": 7,
		"startTime": 9,
		"endTime": 20,
		"minEventOccurences": 20,
    		"speedLimit": 35,
		"snrTarget": 10
	},
	"numeric": {
		"duplicateDetection": [],
		"suppressCols": [],
		"minEventOccurences": 20,
		"groupyByCol": "license_plate"
	}
}
